team_comm_tools/__init__.py
team_comm_tools/feature_builder.py
team_comm_tools/feature_dict.py
team_comm_tools/lambda_function.py
team_comm_tools/features/__init__.py
team_comm_tools/features/basic_features.py
team_comm_tools/features/burstiness.py
team_comm_tools/features/certainty.py
team_comm_tools/features/discursive_diversity.py
team_comm_tools/features/fflow.py
team_comm_tools/features/get_all_DD_features.py
team_comm_tools/features/get_user_network.py
team_comm_tools/features/hedge.py
team_comm_tools/features/info_exchange_zscore.py
team_comm_tools/features/information_diversity.py
team_comm_tools/features/keywords.py
team_comm_tools/features/lexical_features_v2.py
team_comm_tools/features/named_entity_recognition_features.py
team_comm_tools/features/other_lexical_features.py
team_comm_tools/features/politeness_features.py
team_comm_tools/features/politeness_v2.py
team_comm_tools/features/politeness_v2_helper.py
team_comm_tools/features/question_num.py
team_comm_tools/features/readability.py
team_comm_tools/features/reddit_tags.py
team_comm_tools/features/temporal_features.py
team_comm_tools/features/textblob_sentiment_analysis.py
team_comm_tools/features/turn_taking_features.py
team_comm_tools/features/user_centroids.py
team_comm_tools/features/variance_in_DD.py
team_comm_tools/features/within_person_discursive_range.py
team_comm_tools/features/word_mimicry.py
team_comm_tools/features/assets/certainty.pkl
team_comm_tools/features/assets/lexicons_dict.pkl
team_comm_tools/features/assets/nan_vector.txt
team_comm_tools/features/lexicons/dale_chall.txt
team_comm_tools/features/lexicons/function_words.txt
team_comm_tools/features/lexicons/liwc_2015.dic
team_comm_tools/features/lexicons/positive_words_info.txt
team_comm_tools/features/lexicons/question_words.txt
team_comm_tools/features/lexicons/readme_lexicons.md
team_comm_tools/features/lexicons/liwc_lexicons/achievement
team_comm_tools/features/lexicons/liwc_lexicons/adverbs
team_comm_tools-0.1.7.dist-info/licenses/LICENSE
team_comm_tools-0.1.7.dist-info/METADATA
team_comm_tools-0.1.7.dist-info/WHEEL
team_comm_tools-0.1.7.dist-info/entry_points.txt
team_comm_tools-0.1.7.dist-info/top_level.txt
team_comm_tools-0.1.7.dist-info/RECORD
