Metadata-Version: 2.4
Name: team_comm_tools
Version: 0.1.7
Summary: A toolkit that generates a variety of features for team conversation data.
Author-email: Xinlan Emily Hu <xehu@wharton.upenn.edu>, Yuxuan Zhang <yuxuanzh@seas.upenn.edu>
License: MIT License
Project-URL: Homepage, https://teamcommtools.seas.upenn.edu/
Project-URL: Documentation, https://conversational-featurizer.readthedocs.io/en/latest/
Project-URL: Repository, https://github.com/Watts-Lab/team-comm-tools
Keywords: computational social science,teams,communication,conversation,chat,analysis
Requires-Python: >=3.10
License-File: LICENSE
Requires-Dist: chardet>=3.0.4
Requires-Dist: convokit==3.0.0
Requires-Dist: emoji==1.7.0
Requires-Dist: flask==3.0.3
Requires-Dist: fuzzywuzzy==0.18.0
Requires-Dist: gensim>=4.3.3
Requires-Dist: matplotlib>=3.0.0
Requires-Dist: nltk==3.9.1
Requires-Dist: numpy<2.0.0
Requires-Dist: pandas==2.2.2
Requires-Dist: pyphen==0.14.0
Requires-Dist: pytest==8.3.2
Requires-Dist: pytest-runner==6.0.1
Requires-Dist: python-dateutil==2.9.0
Requires-Dist: pytz==2024.1
Requires-Dist: regex==2023.12.25
Requires-Dist: scikit-learn==1.5.1
Requires-Dist: scipy<1.14.0
Requires-Dist: sentence-transformers>=2.3.1
Requires-Dist: sentencepiece>=0.2.0
Requires-Dist: spacy>=3.7.2
Requires-Dist: spacy-legacy==3.0.12
Requires-Dist: spacy-loggers==1.0.5
Requires-Dist: textblob==0.17.1
Requires-Dist: tokenizers==0.19.1
Requires-Dist: torch==2.4.1
Requires-Dist: torchaudio==2.4.1
Requires-Dist: torchvision==0.19.1
Requires-Dist: transformers==4.44.0
Requires-Dist: tqdm>=4.66.5
Requires-Dist: tzdata>=2023.3
Requires-Dist: tzlocal==5.2
Dynamic: license-file
